{
  "meta": {
    "schema_version": 2,
    "source_url": "https://api.coingecko.com/api/v3/simple/price",
    "fetched_at_utc": "2026-06-27 10:20:53 UTC",
    "fetched_at_ist": "2026-06-27 15:50:53 IST",
    "asset_count": 4,
    "content_hash": "6e6190d0a0b5a9e98847be85e14712d577c36c562c1906887d93ea9741ef1609",
    "previous_hash": "6b2fa0fd7fa17ad93c34a74f5c92ae230b75421c041f330d94c7ccf42c708bf2",
    "assets_changed_vs_previous": 4,
    "largest_move_asset": "solana",
    "largest_move_24h": 4.0515
  },
  "assets": {
    "bitcoin": {
      "price_usd": 60364.0,
      "change_24h": 1.0988782102876726
    },
    "ethereum": {
      "price_usd": 1581.39,
      "change_24h": 1.9410423125915948
    },
    "solana": {
      "price_usd": 71.79,
      "change_24h": 4.051512523835133
    },
    "bnb": {
      "price_usd": 563.65,
      "change_24h": -0.15082032251218686
    }
  }
}