{
  "meta": {
    "schema_version": 2,
    "source_url": "https://api.coingecko.com/api/v3/simple/price",
    "fetched_at_utc": "2026-04-02 23:27:22 UTC",
    "fetched_at_ist": "2026-04-03 04:57:22 IST",
    "asset_count": 4,
    "content_hash": "9038db4d969c76bff70370725218fa0d142b03e5d2347b83d736cc78217d75d5",
    "previous_hash": "94373804c8a55f58378de77cfc6b858d8165bdffa7221a9aac2342f641522f7e",
    "assets_changed_vs_previous": 4,
    "largest_move_asset": "bnb",
    "largest_move_24h": -4.4632
  },
  "assets": {
    "bitcoin": {
      "price_usd": 66992.0,
      "change_24h": -1.648270214635004
    },
    "ethereum": {
      "price_usd": 2058.73,
      "change_24h": -3.8174330801556198
    },
    "solana": {
      "price_usd": 79.01,
      "change_24h": -2.7989481001141385
    },
    "bnb": {
      "price_usd": 583.45,
      "change_24h": -4.463152967775939
    }
  }
}