{
  "schema_version": 2,
  "date_ist": "2026-07-13",
  "target_commits_per_day": 100,
  "commits_today": 13,
  "remaining_today": 87,
  "status": "on-track",
  "streak_days": 83,
  "commit_count_source": "git-history",
  "pending_commit_included": 1,
  "last_commit_utc": "2026-07-13 15:50:45 UTC",
  "last_commit_ist": "2026-07-13 21:20:45 IST",
  "last_data_update_utc": "2026-07-13 04:43:18 UTC",
  "last_data_update_ist": "2026-07-13 10:13:18 IST",
  "sources": {
    "github": {
      "label": "GitHub Trending",
      "item_count": 24,
      "last_fetch_utc": "2026-07-11 12:10:43 UTC",
      "last_fetch_ist": "2026-07-11 17:40:43 IST",
      "content_hash": "df9a907e3de79742ee6cb9933753db1f8de7196360338e0a0e0020cf0820e1c8",
      "content_hash_short": "df9a907e3de7",
      "change_flag": true,
      "change_summary": "+24 new repos"
    },
    "hacker_news": {
      "label": "Hacker News",
      "item_count": 5,
      "last_fetch_utc": "2026-07-13 04:43:18 UTC",
      "last_fetch_ist": "2026-07-13 10:13:18 IST",
      "content_hash": "78f1ef0100c579445e89f70bb16f1778b1ebb4aaacf87c2cf1d49fc53b2e73e6",
      "content_hash_short": "78f1ef0100c5",
      "change_flag": true,
      "change_summary": "+4 new stories"
    },
    "crypto": {
      "label": "Crypto",
      "item_count": 4,
      "last_fetch_utc": "2026-07-12 23:27:10 UTC",
      "last_fetch_ist": "2026-07-13 04:57:10 IST",
      "content_hash": "6e009fe4196d8c91d9a69d6e7305636b8b61e9d6762a6c8a4cb0b6da36825b74",
      "content_hash_short": "6e009fe4196d",
      "change_flag": true,
      "change_summary": "4 assets moved"
    }
  }
}