{
  "schema_version": 2,
  "date_ist": "2026-05-05",
  "target_commits_per_day": 100,
  "commits_today": 8,
  "remaining_today": 92,
  "status": "on-track",
  "streak_days": 46,
  "commit_count_source": "git-history",
  "pending_commit_included": 1,
  "last_commit_utc": "2026-05-05 04:36:01 UTC",
  "last_commit_ist": "2026-05-05 10:06:01 IST",
  "last_data_update_utc": "2026-05-05 04:36:00 UTC",
  "last_data_update_ist": "2026-05-05 10:06:00 IST",
  "sources": {
    "github": {
      "label": "GitHub Trending",
      "item_count": 9,
      "last_fetch_utc": "2026-05-04 00:10:09 UTC",
      "last_fetch_ist": "2026-05-04 05:40:09 IST",
      "content_hash": "f8310efa49d325e96b0cc9d06372005062ada84665124781d9d48359082df1c2",
      "content_hash_short": "f8310efa49d3",
      "change_flag": false,
      "change_summary": "+0 new repos"
    },
    "hacker_news": {
      "label": "Hacker News",
      "item_count": 5,
      "last_fetch_utc": "2026-05-05 04:36:00 UTC",
      "last_fetch_ist": "2026-05-05 10:06:00 IST",
      "content_hash": "6ac383efa90e3179b510cf6a498b18fe30d616e4f812971a13b4c80e7498e91d",
      "content_hash_short": "6ac383efa90e",
      "change_flag": true,
      "change_summary": "+4 new stories"
    },
    "crypto": {
      "label": "Crypto",
      "item_count": 4,
      "last_fetch_utc": "2026-05-05 01:17:37 UTC",
      "last_fetch_ist": "2026-05-05 06:47:37 IST",
      "content_hash": "7638ddca6320d09ebaa1058d3ccd02918c7cf6f7f11d5f391325e57e30b20a3c",
      "content_hash_short": "7638ddca6320",
      "change_flag": true,
      "change_summary": "4 assets moved"
    }
  }
}