{
  "schema_version": 2,
  "date_ist": "2026-06-29",
  "target_commits_per_day": 100,
  "commits_today": 8,
  "remaining_today": 92,
  "status": "on-track",
  "streak_days": 78,
  "commit_count_source": "git-history",
  "pending_commit_included": 1,
  "last_commit_utc": "2026-06-29 07:14:47 UTC",
  "last_commit_ist": "2026-06-29 12:44:47 IST",
  "last_data_update_utc": "2026-06-29 12:09:00 UTC",
  "last_data_update_ist": "2026-06-29 17:39:00 IST",
  "sources": {
    "github": {
      "label": "GitHub Trending",
      "item_count": 14,
      "last_fetch_utc": "2026-06-29 12:08:59 UTC",
      "last_fetch_ist": "2026-06-29 17:38:59 IST",
      "content_hash": "c7dee43d5fcdc3ae1669d753947e1b37d7fbba264dddce3df6d9e186fca243fc",
      "content_hash_short": "c7dee43d5fcd",
      "change_flag": true,
      "change_summary": "+14 new repos"
    },
    "hacker_news": {
      "label": "Hacker News",
      "item_count": 5,
      "last_fetch_utc": "2026-06-29 12:09:00 UTC",
      "last_fetch_ist": "2026-06-29 17:39:00 IST",
      "content_hash": "80ce7766ba36081d4d28fc0c38c13c70ccc9cd33af7f439ca6efc3bb43ac831c",
      "content_hash_short": "80ce7766ba36",
      "change_flag": true,
      "change_summary": "+4 new stories"
    },
    "crypto": {
      "label": "Crypto",
      "item_count": 4,
      "last_fetch_utc": "2026-06-29 12:09:00 UTC",
      "last_fetch_ist": "2026-06-29 17:39:00 IST",
      "content_hash": "0bd78fe8679e84100f35f76ee71b1099e30d9a0b5d6ba6ff8658d2e8c3bf342c",
      "content_hash_short": "0bd78fe8679e",
      "change_flag": true,
      "change_summary": "4 assets moved"
    }
  }
}