{
  "schema_version": 2,
  "date_ist": "2026-04-21",
  "target_commits_per_day": 100,
  "commits_today": 16,
  "remaining_today": 84,
  "status": "on-track",
  "streak_days": 41,
  "commit_count_source": "git-history",
  "pending_commit_included": 1,
  "last_commit_utc": "2026-04-21 14:21:37 UTC",
  "last_commit_ist": "2026-04-21 19:51:37 IST",
  "last_data_update_utc": "2026-04-21 14:21:37 UTC",
  "last_data_update_ist": "2026-04-21 19:51:37 IST",
  "sources": {
    "github": {
      "label": "GitHub Trending",
      "item_count": 10,
      "last_fetch_utc": "2026-04-20 12:13:12 UTC",
      "last_fetch_ist": "2026-04-20 17:43:12 IST",
      "content_hash": "9d741dec34970dd3a20de457c9e1a449602a3cd01d9d7f7db7790b6d463764f6",
      "content_hash_short": "9d741dec3497",
      "change_flag": true,
      "change_summary": "+9 new repos"
    },
    "hacker_news": {
      "label": "Hacker News",
      "item_count": 5,
      "last_fetch_utc": "2026-04-21 12:44:52 UTC",
      "last_fetch_ist": "2026-04-21 18:14:52 IST",
      "content_hash": "268d4dd239bd73f9c8244d6a51e844ec93be1f829769b1a1369a5bde83620d7d",
      "content_hash_short": "268d4dd239bd",
      "change_flag": true,
      "change_summary": "+2 new stories"
    },
    "crypto": {
      "label": "Crypto",
      "item_count": 4,
      "last_fetch_utc": "2026-04-21 14:21:37 UTC",
      "last_fetch_ist": "2026-04-21 19:51:37 IST",
      "content_hash": "3e078203903c5aaa627a0f0942880daec4e0efbee6c9043a60e7e3756e529d3d",
      "content_hash_short": "3e078203903c",
      "change_flag": true,
      "change_summary": "4 assets moved"
    }
  }
}